Metadata-Version: 2.1
Name: recordlogger
Version: 0.1.0
Summary: A simple logging utility for recording variable info.
Author: souhardya
Author-email: dandapatsouhardya2004@gmail.com
License: MIT
Classifier: Programming Language :: Python :: 3
Classifier: License :: OSI Approved :: MIT License
Classifier: Operating System :: OS Independent
Requires-Python: >=3.6
License-File: LICENSE
Requires-Dist: inspect
Requires-Dist: os
